cellscope/__init__.py
cellscope/_data/__init__.py
cellscope/_data/genes.json
cellscope/plotting/__init__.py
cellscope/plotting/_annotation.py
cellscope/plotting/_emmbeding.py
cellscope/plotting/_stat.py
cellscope/preprocessing/__init__.py
cellscope/preprocessing/_normalization.py
cellscope/preprocessing/_qc.py
cellscope/tools/__init__.py
cellscope/tools/_trajectory.py
cellscope/tools/cell_type_annotation.py
cellscope/tools/compositional_analysis.py
cellscope/tools/gene_level_analysis.py
cellscope/tools/utils.py
cellscope-1.1.1.dist-info/METADATA
cellscope-1.1.1.dist-info/WHEEL
cellscope-1.1.1.dist-info/licenses/LICENSE
cellscope-1.1.1.dist-info/RECORD
