Metadata-Version: 2.4
Name: cellscope
Version: 1.1.1
Summary: single cell multi-omics data analysis toolkit
Project-URL: Homepage, https://github.com/ScienceAdvances/cellscope
Author-email: 生信探索 BioQuest <yehior@qq.com>
License-File: LICENSE
Classifier: Development Status :: 4 - Beta
Classifier: Intended Audience :: Developers
Classifier: Operating System :: OS Independent
Classifier: Programming Language :: Python :: 3
Classifier: Programming Language :: Python :: 3.10
Requires-Python: >=3.9
Requires-Dist: numpy>1.19.5
Requires-Dist: numpy>1.23
Requires-Dist: pandas>1.5
Requires-Dist: pydeseq2>0.49
Requires-Dist: scanpy>1.10
